lll_simple_ai_service/__init__.py
lll_simple_ai_service/config/__init__.py
lll_simple_ai_service/config/default_config.py
lll_simple_ai_service/core/__init__.py
lll_simple_ai_service/core/schemas.py
lll_simple_ai_service/core/structured_ai.py
lll_simple_ai_service/web/__init__.py
lll_simple_ai_service/web/api.py
lll_simple_ai_service-0.1.2.dist-info/licenses/LICENSE
lll_simple_ai_service-0.1.2.dist-info/METADATA
lll_simple_ai_service-0.1.2.dist-info/WHEEL
lll_simple_ai_service-0.1.2.dist-info/top_level.txt
lll_simple_ai_service-0.1.2.dist-info/RECORD
