Metadata-Version: 2.4
Name: lll-simple-ai-service
Version: 0.1.2
Summary: Structured AI service with Outlines for JSON output
Requires-Python: >=3.8
License-File: LICENSE
Requires-Dist: torch>=2.0.0
Requires-Dist: transformers==4.57.1
Requires-Dist: outlines>=1.2.7
Requires-Dist: flask>=2.0.0
Requires-Dist: requests>=2.25.0
Requires-Dist: huggingface-hub>=0.16.0
Requires-Dist: accelerate>=1.11.0
Requires-Dist: lll-simple-ai-shared>=0.1.4
Dynamic: license-file
